msmath/__init__.py
msmath/bch.py
msmath/bitstring.py
msmath/conversions.py
msmath/ffield.py
msmath/ffpoly.py
msmath/fring.py
msmath/graph.py
msmath/matrix.py
msmath/numfuns.py
msmath/optable.py
msmath/poly.py
msmath/quaternion.py
msmath/rational.py
msmath/share.py
msmath-1.0.21.dist-info/LICENSE
msmath-1.0.21.dist-info/METADATA
msmath-1.0.21.dist-info/WHEEL
msmath-1.0.21.dist-info/top_level.txt
msmath-1.0.21.dist-info/RECORD
