Metadata-Version: 2.1
Name: msmath
Version: 1.0.21
Summary: UNKNOWN
Home-page: https://github.com/ms0/msmath
Author: Mike Speciner
Author-email: ms@alum.mit.edu
License: UNKNOWN
Project-URL: Source, https://github.com/ms0/msmath
Project-URL: Bug Reports, https://github.com/ms0/msmath/issues
Platform: UNKNOWN
Classifier: Development Status :: 5 - Production/Stable
Classifier: Intended Audience :: Education
Classifier: Topic :: Scientific/Engineering :: Mathematics
Classifier: License :: OSI Approved :: GNU General Public License v3 (GPLv3)
Classifier: Programming Language :: Python
